dominantcolor-1.0.0.dist-info/METADATA
dominantcolor-1.0.0.dist-info/WHEEL
dominantcolor.cpython-39-x86_64-linux-gnu.so
dominantcolor-1.0.0.dist-info/RECORD
