Metadata-Version: 2.1
Name: dominantcolor
Version: 1.0.0
Classifier: License :: OSI Approved :: MIT License
Classifier: Programming Language :: Rust
Classifier: Topic :: Multimedia :: Graphics
Summary: Fast & minimal python module to compute the dominant color of an image, written in Rust.
Author: baptiste0928 <contact@baptiste0928.net>
Author-Email: baptiste0928 <contact@baptiste0928.net>
License: MIT
